bbox_utils/__init__.py
bbox_utils/bbox_2d.py
bbox_utils/bbox_3d.py
bbox_utils/image.py
bbox_utils/point_cloud.py
bbox_utils/utils.py
bbox_utils-0.1.1.dist-info/AUTHORS.rst
bbox_utils-0.1.1.dist-info/LICENSE.txt
bbox_utils-0.1.1.dist-info/METADATA
bbox_utils-0.1.1.dist-info/WHEEL
bbox_utils-0.1.1.dist-info/top_level.txt
bbox_utils-0.1.1.dist-info/RECORD
