Metadata-Version: 2.1
Name: bbox-utils
Version: 0.1.1
Summary: Utilities to easily convert between different bounding box formats (YOLO, XYWH, XYXY, etc.).
Home-page: https://github.com/EricWiener/bbox-utils.git
Author: Eric Wiener
Author-email: ericwiener3@gmail.com
License: MIT
Project-URL: Documentation, https://bbox-utils.readthedocs.io/en/latest/
Platform: any
Classifier: Development Status :: 4 - Beta
Classifier: Programming Language :: Python
Requires-Dist: numpy (>=1.13.3)
Requires-Dist: pyquaternion
Requires-Dist: importlib-metadata ; python_version < "3.8"
Provides-Extra: testing
Requires-Dist: setuptools ; extra == 'testing'
Requires-Dist: pytest ; extra == 'testing'
Requires-Dist: pytest-cov ; extra == 'testing'
Requires-Dist: numpy (>=1.13.3) ; extra == 'testing'
Requires-Dist: pillow ; extra == 'testing'
Requires-Dist: pyquaternion ; extra == 'testing'
Requires-Dist: open3d ; extra == 'testing'
Requires-Dist: plotly (==4.14.3) ; extra == 'testing'
Requires-Dist: opencv-python ; extra == 'testing'
